Metadata-Version: 1.1
Name: mozilla-srgutil
Version: 0.2.0
Summary: SRG utilities
Home-page: https://github.com/mozilla/srgutil
Author: Mozilla Foundation
Author-email: fx-data-dev@mozilla.org
License: MPL 2.0
Platform: UNKNOWN
Classifier: Development Status :: 3 - Alpha
Classifier: Environment :: Web Environment :: Mozilla
Classifier: Intended Audience :: Developers
Classifier: License :: OSI Approved :: Mozilla Public License 2.0 (MPL 2.0)
Classifier: Programming Language :: Python
Classifier: Programming Language :: Python :: 2
Classifier: Programming Language :: Python :: 2.7
Classifier: Programming Language :: Python :: 3
Classifier: Programming Language :: Python :: 3.6
Classifier: Programming Language :: Python :: 3.7
Classifier: Topic :: Internet :: WWW/HTTP
Classifier: Topic :: Scientific/Engineering :: Information Analysis
